jxl9754_package/__init__.py
jxl9754_package/module1.py
jxl9754_package/module2.py
mypackage/__init__.py
mypackage/module1.py
mypackage/module2.py
jxl9754_package-0.1.dist-info/METADATA
jxl9754_package-0.1.dist-info/WHEEL
jxl9754_package-0.1.dist-info/top_level.txt
jxl9754_package-0.1.dist-info/RECORD
