Metadata-Version: 2.1
Name: jxl9754_package
Version: 0.1
Summary: A sample Python package
Author: John Doe
Author-email: jdoe@example.com
Requires-Dist: numpy
Requires-Dist: pandas
